nonebot_plugin_BitTorrent/__init__.py
nonebot_plugin_BitTorrent/config.py
nonebot_plugin_BitTorrent/utils.py
nonebot_plugin_BitTorrent-0.0.21.dist-info/LICENSE
nonebot_plugin_BitTorrent-0.0.21.dist-info/METADATA
nonebot_plugin_BitTorrent-0.0.21.dist-info/WHEEL
nonebot_plugin_BitTorrent-0.0.21.dist-info/top_level.txt
nonebot_plugin_BitTorrent-0.0.21.dist-info/RECORD
