Metadata-Version: 2.1
Name: nonebot_plugin_BitTorrent
Version: 0.0.21
Summary: encapsulate logger
Home-page: https://github.com/Special-Week/nonebot_plugin_BitTorrent
Author: Special-Week
Author-email: 2749903559@qq.com
Requires-Python: >=3.8.0
License-File: LICENSE
Requires-Dist: lxml
Requires-Dist: httpx
Requires-Dist: bs4
Requires-Dist: nonebot2
Requires-Dist: nonebot-adapter-onebot
